{
  "displayName": "CIS - Ensure time synchronization is in use (ntp)",
  "enabled": true,
  "id": "6f8935a2-58b6-4bad-85da-48086de548de",
  "longDescription": "",
  "parameters": {
    "section": {
      "name": "sections",
      "sections": [
        {
          "section": {
            "name": "Technique parameters",
            "vars": [
              {
                "var": {
                  "name": "3DC0EB13-0FD2-426A-9965-84E35AA3F51B",
                  "value": "/bin/true"
                }
              },
              {
                "var": {
                  "name": "A1B9E560-A2C8-4759-9F93-99F05D48B14F",
                  "value": "ntp"
                }
              }
            ]
          }
        }
      ]
    }
  },
  "shortDescription": "",
  "techniqueName": "CIS_debian9___Ensure_a_package_is_installed",
  "techniqueVersion": "1.0"
}