{
  "displayName": " CIS - Ensure AIDE is installed",
  "enabled": true,
  "id": "62e7a743-e72b-4977-97d2-fbe7582dfe3b",
  "longDescription": "Description: AIDE takes a snapshot of filesystem state including modification times, permissions, and file hashes which can then be used to compare against the current state of the filesystem to detect modifications to the system. Rationale: By monitoring the filesystem state compromised files can be detected to prevent or limit the exposure of accidental or malicious misconfigurations or modified binaries.",
  "parameters": {
    "section": {
      "name": "sections",
      "sections": [
        {
          "section": {
            "name": "Technique parameters",
            "vars": [
              {
                "var": {
                  "name": "3DC0EB13-0FD2-426A-9965-84E35AA3F51B",
                  "value": "aide --init && mv /var/lib/aide/aide.db.new.gz /var/lib/aide/aide.db.gz"
                }
              },
              {
                "var": {
                  "name": "A1B9E560-A2C8-4759-9F93-99F05D48B14F",
                  "value": "aide"
                }
              }
            ]
          }
        }
      ]
    }
  },
  "shortDescription": "",
  "techniqueName": "CIS_debian10___Ensure_a_package_is_installed",
  "techniqueVersion": "1.0"
}